{
    "display_information": {
        "name": "Daily Dose",
        "description": "Automated daily standup bot for teams with multi-tenant organization support",
        "background_color": "#2c3e50",
        "long_description": "Daily Dose helps teams stay connected with automated daily standups. Features include scheduled reminders, team management, leave tracking, and comprehensive standup reporting across multiple organizations."
    },
    "features": {
        "bot_user": {
            "display_name": "Daily Dose",
            "always_online": true
        },
        "slash_commands": [
            {
                "command": "/dd-team-create",
                "url": "{{APP_URL}}/slack/events",
                "description": "Create a new team with standup schedule",
                "usage_hint": "[TeamName] 09:30 10:00",
                "should_escape": false
            },
            {
                "command": "/dd-team-join",
                "url": "{{APP_URL}}/slack/events",
                "description": "Join a team",
                "usage_hint": "[TeamName]",
                "should_escape": false
            },
            {
                "command": "/dd-team-leave",
                "url": "{{APP_URL}}/slack/events",
                "description": "Leave a team",
                "usage_hint": "[TeamName]",
                "should_escape": false
            },
            {
                "command": "/dd-team-list",
                "url": "{{APP_URL}}/slack/events",
                "description": "List all teams in your organization",
                "should_escape": false
            },
            {
                "command": "/dd-team-members",
                "url": "{{APP_URL}}/slack/events",
                "description": "View team members",
                "usage_hint": "[TeamName]",
                "should_escape": false
            },
            {
                "command": "/dd-team-update",
                "url": "{{APP_URL}}/slack/events",
                "description": "Update team settings (admin only)",
                "usage_hint": "[TeamName] name=NewName standup=09:00",
                "should_escape": false
            },
            {
                "command": "/dd-leave-set",
                "url": "{{APP_URL}}/slack/events",
                "description": "Set leave dates to skip standup reminders",
                "usage_hint": "YYYY-MM-DD [YYYY-MM-DD] [reason]",
                "should_escape": false
            },
            {
                "command": "/dd-leave-cancel",
                "url": "{{APP_URL}}/slack/events",
                "description": "Cancel previously set leave",
                "usage_hint": "leave-id",
                "should_escape": false
            },
            {
                "command": "/dd-leave-list",
                "url": "{{APP_URL}}/slack/events",
                "description": "List your upcoming leaves",
                "should_escape": false
            },
            {
                "command": "/dd-workdays-set",
                "url": "{{APP_URL}}/slack/events",
                "description": "Set your personal work days",
                "usage_hint": "1,2,3,4,7 (1=Mon, 7=Sun)",
                "should_escape": false
            },
            {
                "command": "/dd-workdays-show",
                "url": "{{APP_URL}}/slack/events",
                "description": "Show your current work day settings",
                "should_escape": false
            },
            {
                "command": "/dd-standup",
                "url": "{{APP_URL}}/slack/events",
                "description": "Submit standup manually outside scheduled time",
                "usage_hint": "[TeamName]",
                "should_escape": false
            },
            {
                "command": "/dd-standup-update",
                "url": "{{APP_URL}}/slack/events",
                "description": "Update standup for any day (default today)",
                "usage_hint": "TeamName [YYYY-MM-DD]",
                "should_escape": false
            },
            {
                "command": "/dd-holiday-set",
                "url": "{{APP_URL}}/slack/events",
                "description": "Set holidays for single day or date range (admin only)",
                "usage_hint": "YYYY-MM-DD [YYYY-MM-DD] [name]",
                "should_escape": false
            },
            {
                "command": "/dd-holiday-update",
                "url": "{{APP_URL}}/slack/events",
                "description": "Update existing holiday name (admin only)",
                "usage_hint": "YYYY-MM-DD new name",
                "should_escape": false
            },
            {
                "command": "/dd-holiday-delete",
                "url": "{{APP_URL}}/slack/events",
                "description": "Delete holidays for single day or date range (admin only)",
                "usage_hint": "YYYY-MM-DD [YYYY-MM-DD]",
                "should_escape": false
            },
            {
                "command": "/dd-holiday-list",
                "url": "{{APP_URL}}/slack/events",
                "description": "List holidays for any date range or time period",
                "usage_hint": "[YYYY|YYYY-MM|YYYY-MM-DD] [YYYY-MM-DD]",
                "should_escape": false
            },
            {
                "command": "/dd-standup-reminder",
                "url": "{{APP_URL}}/slack/events",
                "description": "Opt in/out of standup non-responded list",
                "usage_hint": "TeamName [on|off]",
                "should_escape": false
            }
        ]
    },
    "oauth_config": {
        "scopes": {
            "bot": [
                "channels:read",
                "chat:write",
                "chat:write.public",
                "commands",
                "users:read",
                "users:read.email",
                "im:write",
                "im:read",
                "groups:read",
                "app_mentions:read",
                "channels:history",
                "groups:history",
                "im:history",
                "mpim:history",
                "team:read"
            ]
        }
    },
    "settings": {
        "event_subscriptions": {
            "request_url": "{{APP_URL}}/slack/events",
            "bot_events": [
                "app_mention",
                "message.channels",
                "message.groups",
                "message.im",
                "team_join"
            ]
        },
        "interactivity": {
            "is_enabled": true,
            "request_url": "{{APP_URL}}/slack/events"
        },
        "org_deploy_enabled": true,
        "socket_mode_enabled": false,
        "token_rotation_enabled": false
    }
}